symMaps/__init__.py
symMaps/base.py
symMaps/lpModels.py
symMaps/lpSys.py
symMaps/mBasic.py
symMaps/simpleSys.py
symmaps-0.0.4.dist-info/licenses/LICENSE
symmaps-0.0.4.dist-info/METADATA
symmaps-0.0.4.dist-info/WHEEL
symmaps-0.0.4.dist-info/top_level.txt
symmaps-0.0.4.dist-info/RECORD
